{
  "TranslationProperties": {
    "Name": "server.items.OneBlock_Unlock_Snow_Plant_Frost_Fern.name",
    "Description": "server.items.OneBlock_Unlock_Snow_Plant_Frost_Fern.description"
  },
  "Id": "OneBlock_Unlock_Snow_Plant_Frost_Fern",
  "ItemLevel": 1,
  "Icon": "Icons/ItemsGenerated/ExpeditionKey.png",
  "Categories": [
    "Items.RecipeDrop"
  ],
  "PlayerAnimationsId": "Item",
  "Recipe": {
    "Input": [
      {
        "ItemId": "Block_Snow",
        "Quantity": 16
      }
    ],
    "OutputQuantity": 1,
    "BenchRequirement": [
      {
        "Type": "Crafting",
        "Categories": [
          "OneBlock_Bench_Snow_Tier1"
        ],
        "Id": "OneBlock_Bench_Snow"
      }
    ]
  },
  "Consumable": true,
  "Tags": {
    "Type": [
      "OneBlock_Unlock_Consumable"
    ],
    "OneBlockUnlockExpedition": [
      "Snow"
    ],
    "OneBlockUnlockDropId": [
      "Plant_Frost_Fern"
    ],
    "OneBlockUnlockWeight": [
      "10"
    ]
  },
  "MaxStack": 1,
  "Quality": "Common"
}