{
  "TranslationProperties": {
    "Name": "items.OneBlock_Unlock_Jungle_Wood_Banyan_Trunk.name",
    "Description": "items.OneBlock_Unlock_Jungle_Wood_Banyan_Trunk.description"
  },
  "Id": "OneBlock_Unlock_Jungle_Wood_Banyan_Trunk",
  "ItemLevel": 1,
  "Icon": "Icons/ItemsGenerated/ExpeditionKey.png",
  "Categories": [
    "Items.RecipeDrop"
  ],
  "PlayerAnimationsId": "Item",
  "Recipe": {
    "Input": [
      {
        "ItemId": "Wood_Jungle_Trunk",
        "Quantity": 16
      }
    ],
    "OutputQuantity": 1,
    "BenchRequirement": [
      {
        "Type": "Crafting",
        "Categories": [
          "OneBlock_Bench_Jungle_Tier1"
        ],
        "Id": "OneBlock_Bench_Jungle"
      }
    ]
  },
  "Consumable": true,
  "Tags": {
    "Type": [
      "OneBlock_Unlock_Consumable"
    ],
    "OneBlockUnlockExpedition": [
      "Jungle"
    ],
    "OneBlockUnlockDropId": [
      "Wood_Banyan_Trunk"
    ],
    "OneBlockUnlockWeight": [
      "10"
    ]
  },
  "MaxStack": 1,
  "Quality": "Common"
}
