{
  "TranslationProperties": {
    "Name": "items.OneBlock_Unlock_Graveyard_Plant_Bramble_Moss_Twisted.name",
    "Description": "items.OneBlock_Unlock_Graveyard_Plant_Bramble_Moss_Twisted.description"
  },
  "Id": "OneBlock_Unlock_Graveyard_Plant_Bramble_Moss_Twisted",
  "ItemLevel": 1,
  "Icon": "Icons/ItemsGenerated/ExpeditionKey.png",
  "Categories": [
    "Items.RecipeDrop"
  ],
  "PlayerAnimationsId": "Item",
  "Recipe": {
    "Input": [
      {
        "ItemId": "Rock_Stone_Mossy",
        "Quantity": 16
      }
    ],
    "OutputQuantity": 1,
    "BenchRequirement": [
      {
        "Type": "Crafting",
        "Categories": [
          "OneBlock_Bench_Graveyard_Tier1"
        ],
        "Id": "OneBlock_Bench_Graveyard"
      }
    ]
  },
  "Consumable": true,
  "Tags": {
    "Type": [
      "OneBlock_Unlock_Consumable"
    ],
    "OneBlockUnlockExpedition": [
      "Graveyard"
    ],
    "OneBlockUnlockDropId": [
      "Plant_Bramble_Moss_Twisted"
    ],
    "OneBlockUnlockWeight": [
      "10"
    ]
  },
  "MaxStack": 1,
  "Quality": "Common"
}
